{
  "$schema": "https://wails.io/schemas/config.v2.json",
  "name": "relief",
  "outputfilename": "relief",
  "frontend:install": "npm install",
  "frontend:build": "npm run build",
  "frontend:dev:watcher": "npm run dev",
  "frontend:dev:serverUrl": "auto",
  "author": {
    "name": "Omelete",
    "email": "dev@omelete.com"
  },
  "info": {
    "companyName": "Omelete",
    "productName": "Relief Orchestrator",
    "productVersion": "0.1.0",
    "copyright": "Copyright © 2026 Omelete",
    "comments": "Ferramenta de orquestração de desenvolvimento local híbrida"
  },
  "nsisType": "multiple",
  "assetdir": "frontend/dist",
  "reloaddirs": "frontend/src",
  "mac": {
    "icon": "build/darwin/appicon.icns"
  },
  "windows": {
    "icon": "build/appicon.ico",
    "webviewIsTransparent": false,
    "windowIsTranslucent": false
  },
  "linux": {
    "icon": "build/appicon.png"
  }
}